django_ipfs_storage-0.0.4.dist-info/DESCRIPTION.rst
django_ipfs_storage-0.0.4.dist-info/METADATA
django_ipfs_storage-0.0.4.dist-info/RECORD
django_ipfs_storage-0.0.4.dist-info/WHEEL
django_ipfs_storage-0.0.4.dist-info/metadata.json
django_ipfs_storage-0.0.4.dist-info/top_level.txt
ipfs_storage/__init__.py
