Metadata-Version: 1.1
Name: django-ipfs-storage
Version: 0.0.4
Summary: IPFS storage backend for Django.
Home-page: https://github.com/jeffbr13/django-ipfs-storage
Author: Ben Jeffrey
Author-email: mail@benjeffrey.net
License: MPL 2.0
Keywords: django ipfs storage
Platform: UNKNOWN
Classifier: Development Status :: 3 - Alpha
Classifier: Programming Language :: Python :: 3
Classifier: Intended Audience :: Developers
Classifier: License :: OSI Approved :: Mozilla Public License 2.0 (MPL 2.0)
Classifier: Framework :: Django
